topsis/__init__.py
topsis/topsis.py
102203594_topsis-0.1.0.dist-info/METADATA
102203594_topsis-0.1.0.dist-info/WHEEL
102203594_topsis-0.1.0.dist-info/top_level.txt
102203594_topsis-0.1.0.dist-info/RECORD
