Metadata-Version: 2.2
Name: 102203594_topsis
Version: 0.1.0
Summary: A Python implementation of the TOPSIS 
Home-page: https://github.com/ShauryaJ123/topsis
Author: Shaurya Jain
Author-email: sjain_be22@example.com
Classifier: Programming Language :: Python :: 3
Classifier: License :: OSI Approved :: MIT License
Classifier: Operating System :: OS Independent
Requires-Python: >=3.6
Requires-Dist: numpy>=1.21.0
Dynamic: author
Dynamic: author-email
Dynamic: classifier
Dynamic: description
Dynamic: description-content-type
Dynamic: home-page
Dynamic: requires-dist
Dynamic: requires-python
Dynamic: summary
